{
  "channel_name": "Christ Presbyterian Church",
  "channel_handle": "@CPCNewHaven",
  "channel_id": "",
  "subscribers": 257,
  "video_count": 446,
  "description": "Aspiring to be a gospel-centered community, we talk a lot about making this a \"safe place\" for real-time sinful people to be in journey with Christ. We hope you feel at home here and in our experience of grace-centered worship.",
  "website": "cpcnewhaven.org",
  "channel_url": "https://www.youtube.com/@CPCNewHaven",
  "last_updated": "2026-01-31"
}

